grsh_data_api/__init__.py
grsh_data_api/api.cp39-win_amd64.pyd
grsh_data_api/auto.cp39-win_amd64.pyd
grsh_data_api/base.cp39-win_amd64.pyd
grsh_data_api/chart.cp39-win_amd64.pyd
grsh_data_api/util.cp39-win_amd64.pyd
grsh_data_api/_mychart/__init__.cp39-win_amd64.pyd
grsh_data_api/_mychart/__init__.py
grsh_data_api/_mychart/_config_color.xlsx
grsh_data_api/_mychart/_solar_lunar_mapping.csv
grsh_data_api/_mychart/base.cp39-win_amd64.pyd
grsh_data_api/_mychart/grammar.cp39-win_amd64.pyd
grsh_data_api/_mychart/grammar_find_used_id.cp39-win_amd64.pyd
grsh_data_api/_mychart/h_grammar_to_list.py
grsh_data_api/_mychart/util.cp39-win_amd64.pyd
grsh_data_api/_mychart/chart/__init__.py
grsh_data_api/_mychart/chart/bar_multi_group.cp39-win_amd64.pyd
grsh_data_api/_mychart/chart/bar_multi_stacked.cp39-win_amd64.pyd
grsh_data_api/_mychart/chart/bar_single.cp39-win_amd64.pyd
grsh_data_api/_mychart/chart/empty.cp39-win_amd64.pyd
grsh_data_api/_mychart/chart/hist.cp39-win_amd64.pyd
grsh_data_api/_mychart/chart/line_lunar_season.cp39-win_amd64.pyd
grsh_data_api/_mychart/chart/line_multi.cp39-win_amd64.pyd
grsh_data_api/_mychart/chart/line_multi_xaxis.cp39-win_amd64.pyd
grsh_data_api/_mychart/chart/line_multi_yaxis.cp39-win_amd64.pyd
grsh_data_api/_mychart/chart/line_season.cp39-win_amd64.pyd
grsh_data_api/_mychart/chart/line_season_area.cp39-win_amd64.pyd
grsh_data_api/_mychart/chart/line_season_week.cp39-win_amd64.pyd
grsh_data_api/_mychart/chart/line_single.cp39-win_amd64.pyd
grsh_data_api/_mychart/chart/line_twinx.cp39-win_amd64.pyd
grsh_data_api/_mychart/chart/table.cp39-win_amd64.pyd
grsh_data_api/_mychart/chart/table_summary.cp39-win_amd64.pyd
grsh_data_api/_mychart/chart/template1_line_with_yoy.cp39-win_amd64.pyd
grsh_data_api/_mychart/chart/template2_two_line_compare_area.cp39-win_amd64.pyd
grsh_data_api/_mychart/chart/template3_two_line_compare_bar.cp39-win_amd64.pyd
grsh_data_api/_mychart/chart/template4_bar_with_yoy.cp39-win_amd64.pyd
grsh_data_api-0.3.9.dist-info/METADATA
grsh_data_api-0.3.9.dist-info/WHEEL
grsh_data_api-0.3.9.dist-info/top_level.txt
grsh_data_api-0.3.9.dist-info/RECORD
