Metadata-Version: 2.1
Name: grsh-data-api
Version: 0.3.9
Summary: grsh_data_api
Home-page: http://none.com
Author: neo
Author-email: none@none.com
Requires-Dist: certifi
Requires-Dist: charset-normalizer
Requires-Dist: idna
Requires-Dist: numpy
Requires-Dist: pandas
Requires-Dist: python-dateutil
Requires-Dist: pytz
Requires-Dist: requests
Requires-Dist: six
Requires-Dist: tzdata
Requires-Dist: urllib3
Requires-Dist: pydantic
Requires-Dist: loguru
Requires-Dist: matplotlib
Requires-Dist: openpyxl
Requires-Dist: PyJWT
Requires-Dist: cryptography
Requires-Dist: ntplib
Requires-Dist: pyparsing
